{
  "states": [
    {
      "name": "do_circleL",
      "attributes": {
        "radius": 0.95
      }
    },
    {
      "name": "do_backward",
      "attributes": {
        "distance": 4.5
      }
    },
    {
      "name": "do_threepoint"
    },
    {
      "name": "do_forward",
      "attributes": {
        "distance": 3.20
      }
    },
    {
      "name": "do_forward",
      "attributes": {
        "distance": 3.0
      }
    },
    {
      "name": "do_circleR",
      "attributes": {
        "radius": 1.7
      }
    },
    {
      "name": "do_turnL"
    },
    {
      "name": "do_turnR"
    },
    {
      "name": "do_turnL"
    }
  ]
}
